Workbook

Sheet 1. Cadastro de Insumos
A1: Ingrediente | B1: Marca/Tipo | C1: Unidade (kg, ml, un) | D1: Qtd na Embalagem | E1: Preço de Compra (R$) | F1: Custo Unitário (R$)
A2: TRIGO | B2: ANIELLA | C2: kg | D2: 5000 | E2: 14 | F2: =IF(AND(D2>0, E2>0), E2/D2, 0) -> 0.0028
A3: AÇÚCAR | B3: PORTO BELLO | C3: kg | D3: 5000 | E3: 20 | F3: =IF(AND(D3>0, E3>0), E3/D3, 0) -> 0.004
A4: OVO | B4: Q/UM | C4: dz | D4: 30 | E4: 20 | F4: =IF(AND(D4>0, E4>0), E4/D4, 0) -> 0.66666667
A5: FERMENTO | B5: ROYAL | C5: PT | D5: 250 | E5: 11 | F5: =IF(AND(D5>0, E5>0), E5/D5, 0) -> 0.044
A6: EMUSTAB | B6: 4 RODAS | C6: KG | D6: 1000 | E6: 45 | F6: =IF(AND(D6>0, E6>0), E6/D6, 0) -> 0.045
F7: =IF(AND(D7>0, E7>0), E7/D7, 0) -> 0
A8: RECHEIOS
A9: LEITE CONDENSADO | B9: tirol | C9: cx | D9: 395 | E9: 6 | F9: =IF(AND(D9>0, E9>0), E9/D9, 0) -> 0.015189873
A10: CREME DE LEITE | B10: tirol | C10: cx | D10: 200 | E10: 3 | F10: =IF(AND(D10>0, E10>0), E10/D10, 0) -> 0.015
A11: CHOCOLATE EM PÓ | B11: MELKEN | C11: KG | D11: 1000 | E11: 80 | F11: =IF(AND(D11>0, E11>0), E11/D11, 0) -> 0.08
A12: COCO | B12: DO VALLE | C12: KG | D12: 1000 | E12: 55 | F12: =IF(AND(D12>0, E12>0), E12/D12, 0) -> 0.055
A13: AMENDOIM | B13: VARIADO | C13: KG | D13: 1000 | E13: 30 | F13: =IF(AND(D13>0, E13>0), E13/D13, 0) -> 0.03
A14: LEITE EM PÓ | B14: NINHO | C14: GR | D14: 400 | E14: 20 | F14: =IF(AND(D14>0, E14>0), E14/D14, 0) -> 0.05
A15: MORANGO | B15: CX | C15: CX | D15: 250 | E15: 15 | F15: =IF(AND(D15>0, E15>0), E15/D15, 0) -> 0.06
A16: BOMBOM OURO BRANCO | B16: LACTA | C16: PT | D16: 50 | E16: 70 | F16: =IF(AND(D16>0, E16>0), E16/D16, 0) -> 1.4
A17: BOMBOM SONHO DE VALSA | B17: LACTA | C17: PT | D17: 50 | E17: 70 | F17: =IF(AND(D17>0, E17>0), E17/D17, 0) -> 1.4
F18: =IF(AND(D18>0, E18>0), E18/D18, 0) -> 0

Sheet 2. Ficha Técnica
B2: RECEITA: | C2: BOLO DE BRIGADEIRO BRANCO 1 KG | G2: PREÇO FINAL DE VENDA SUGERIDO
B4: Ingrediente | C4: Qtd na Receita | D4: Custo Unitário (R$) | E4: Subtotal Item (R$) | G4: Item de Custo | H4: Valor/Taxa | I4: Subtotal (R$)
B5: trigo | C5: 175 | D5: ='1. Cadastro de Insumos'!E2/'1. Cadastro de Insumos'!D2 -> 0.0028 | E5: =C5*D5 -> 0.49 | G5: Custo de Insumos (Automático) | I5: =E16 -> 16.428333
B6: açúcar | C6: 150 | D6: ='1. Cadastro de Insumos'!E3/'1. Cadastro de Insumos'!D3 -> 0.004 | E6: =C6*D6 -> 0.6 | G6: Custos Fixos/Utilidades (Gás/Luz) - % | H6: 0.1 | I6: =I5*H6 -> 1.6428333
B7: ovo | C7: 3.5 | D7: ='1. Cadastro de Insumos'!E4/'1. Cadastro de Insumos'!D4 -> 0.66666667 | E7: =C7*D7 -> 2.3333333 | G7: Mão de Obra (Pro-labore) - % | H7: 0.2 | I7: =(I5+I6)*H7 -> 3.6142333
B8: fermento | C8: 7.5 | D8: ='1. Cadastro de Insumos'!E5/'1. Cadastro de Insumos'!D5 -> 0.044 | E8: =C8*D8 -> 0.33 | G8: SUBTOTAL (CUSTO DE PRODUÇÃO) | I8: =SUM(I5:I7) -> 21.6854
B9: emustab | C9: 15 | D9: ='1. Cadastro de Insumos'!E6/'1. Cadastro de Insumos'!D6 -> 0.045 | E9: =C9*D9 -> 0.675 | G9: Margem de Lucro Desejada - % | H9: 1.5
E10: =SUM(E5:E9) -> 4.4283333 | G10: TOTAL | I10: =I8*(1+H9) -> 54.2135
B11: RECHEIO
B12: leite condensado | C12: 1 | D12: ='1. Cadastro de Insumos'!E9*C12 -> 6 | E12: =C12*D12 -> 6 | G12: Embalagem e Descartáveis | H12: 1 | I12: 2.5
B13: creme de leite | C13: 2 | D13: ='1. Cadastro de Insumos'!E10 -> 3 | E13: =C13*D13 -> 6
E14: =C14*D14 -> 0 | G14: PREÇO FINAL DE VENDA SUGERIDO | I14: =SUM(I10:I13) -> 56.7135
E15: =SUM(E12:E14) -> 12
C16: CUSTO TOTAL DE INSUMOS: | E16: =SUM(E10,E15) -> 16.428333
B21: RECEITA: | C21: BOLO DE BRIGADEIRO DE CHOCOLATE 1 KG | G21: PREÇO FINAL DE VENDA SUGERIDO
B23: Ingrediente | C23: Qtd na Receita | D23: Custo Unitário (R$) | E23: Subtotal Item (R$) | G23: Item de Custo | H23: Valor/Taxa | I23: Subtotal (R$)
B24: trigo | C24: 175 | D24: ='1. Cadastro de Insumos'!F2 -> 0.0028 | E24: =C24*D24 -> 0.49 | G24: Custo de Insumos (Automático) | I24: =SUM(E29:E33) -> 16.428333
B25: açúcar | C25: 150 | D25: ='1. Cadastro de Insumos'!F3 -> 0.004 | E25: =C25*D25 -> 0.6 | G25: Custos Fixos/Utilidades (Gás/Luz) - % | H25: 0.1 | I25: =I24*H25 -> 1.6428333
B26: ovo | C26: 3.5 | D26: ='1. Cadastro de Insumos'!F4 -> 0.66666667 | E26: =C26*D26 -> 2.3333333 | G26: Mão de Obra (Pro-labore) - % | H26: 0.2 | I26: =(I24+I25)*H26 -> 3.6142333
B27: fermento | C27: 7.5 | D27: ='1. Cadastro de Insumos'!F5 -> 0.044 | E27: =C27*D27 -> 0.33 | G27: SUBTOTAL (CUSTO DE PRODUÇÃO) | I27: =SUM(I24:I26) -> 21.6854
B28: emustab | C28: 15 | D28: ='1. Cadastro de Insumos'!F6 -> 0.045 | E28: =C28*D28 -> 0.675 | G28: Margem de Lucro Desejada - % | H28: 1.5
E29: =SUM(E24:E28) -> 4.4283333 | G29: TOTAL | I29: =I27*(1+H28) -> 54.2135
B31: RECHEIO | G31: CHOCOLATE EM PÓ | I31: =E34 -> 4.8
B32: leite condensado | C32: 1 | D32: ='1. Cadastro de Insumos'!E9 -> 6 | E32: =C32*D32 -> 6 | G32: Embalagem e Descartáveis | H32: 1 | I32: 2.5
B33: creme de leite | C33: 2 | D33: ='1. Cadastro de Insumos'!E10 -> 3 | E33: =C33*D33 -> 6
B34: CHOCOLATE EM PÓ | C34: 60 | D34: ='1. Cadastro de Insumos'!F11 -> 0.08 | E34: =C34*D34 -> 4.8 | G34: PREÇO FINAL DE VENDA SUGERIDO | I34: =SUM(I29:I33) -> 61.5135
E35: =SUM(E32:E34) -> 16.8
C36: CUSTO TOTAL DE INSUMOS: | E36: =SUM(E29,E35) -> 21.228333
B41: RECEITA: | C41: BOLO DE BEJINHO 1 KG | G41: PREÇO FINAL DE VENDA SUGERIDO
B43: Ingrediente | C43: Qtd na Receita | D43: Custo Unitário (R$) | E43: Subtotal Item (R$) | G43: Item de Custo | H43: Valor/Taxa | I43: Subtotal (R$)
B44: trigo | C44: 175 | D44: ='1. Cadastro de Insumos'!F2 -> 0.0028 | E44: =C44*D44 -> 0.49 | G44: Custo de Insumos (Automático) | I44: =SUM(E49:E53) -> 16.428333
B45: açúcar | C45: 150 | D45: ='1. Cadastro de Insumos'!F3 -> 0.004 | E45: =C45*D45 -> 0.6 | G45: Custos Fixos/Utilidades (Gás/Luz) - % | H45: 0.1 | I45: =I44*H45 -> 1.6428333
B46: ovo | C46: 3.5 | D46: ='1. Cadastro de Insumos'!F4 -> 0.66666667 | E46: =C46*D46 -> 2.3333333 | G46: Mão de Obra (Pro-labore) - % | H46: 0.2 | I46: =(I44+I45)*H46 -> 3.6142333
B47: fermento | C47: 7.5 | D47: ='1. Cadastro de Insumos'!F5 -> 0.044 | E47: =C47*D47 -> 0.33 | G47: SUBTOTAL (CUSTO DE PRODUÇÃO) | I47: =SUM(I44:I46) -> 21.6854
B48: emustab | C48: 15 | D48: ='1. Cadastro de Insumos'!F6 -> 0.045 | E48: =C48*D48 -> 0.675 | G48: Margem de Lucro Desejada - % | H48: 1.5
E49: =SUM(E44:E48) -> 4.4283333 | G49: TOTAL | I49: =I47*(1+H48) -> 54.2135
B51: RECHEIO | G51: COCO | I51: =E54 -> 5.5
B52: leite condensado | C52: 1 | D52: ='1. Cadastro de Insumos'!E9 -> 6 | E52: =C52*D52 -> 6 | G52: Embalagem e Descartáveis | H52: 1 | I52: 2.5
B53: creme de leite | C53: 2 | D53: ='1. Cadastro de Insumos'!E10 -> 3 | E53: =C53*D53 -> 6
B54: COCO | C54: 100 | D54: ='1. Cadastro de Insumos'!F12 -> 0.055 | E54: =C54*D54 -> 5.5 | G54: PREÇO FINAL DE VENDA SUGERIDO | I54: =SUM(I49:I53) -> 62.2135
E55: =SUM(E52:E54) -> 17.5
C56: CUSTO TOTAL DE INSUMOS: | E56: =SUM(E49,E55) -> 21.928333
B61: RECEITA: | C61: BOLO DE SONHO DE VALSA 1 KG | G61: PREÇO FINAL DE VENDA SUGERIDO
B63: Ingrediente | C63: Qtd na Receita | D63: Custo Unitário (R$) | E63: Subtotal Item (R$) | G63: Item de Custo | H63: Valor/Taxa | I63: Subtotal (R$)
B64: trigo | C64: 175 | D64: ='1. Cadastro de Insumos'!F2 -> 0.0028 | E64: =C64*D64 -> 0.49 | G64: Custo de Insumos (Automático) | I64: =SUM(E69:E73) -> 16.428333
B65: açúcar | C65: 150 | D65: ='1. Cadastro de Insumos'!F3 -> 0.004 | E65: =C65*D65 -> 0.6 | G65: Custos Fixos/Utilidades (Gás/Luz) - % | H65: 0.1 | I65: =I64*H65 -> 1.6428333
B66: ovo | C66: 3.5 | D66: ='1. Cadastro de Insumos'!F4 -> 0.66666667 | E66: =C66*D66 -> 2.3333333 | G66: Mão de Obra (Pro-labore) - % | H66: 0.2 | I66: =(I64+I65)*H66 -> 3.6142333
B67: fermento | C67: 7.5 | D67: ='1. Cadastro de Insumos'!F5 -> 0.044 | E67: =C67*D67 -> 0.33 | G67: SUBTOTAL (CUSTO DE PRODUÇÃO) | I67: =SUM(I64:I66) -> 21.6854
B68: emustab | C68: 15 | D68: ='1. Cadastro de Insumos'!F6 -> 0.045 | E68: =C68*D68 -> 0.675 | G68: Margem de Lucro Desejada - % | H68: 1.5
E69: =SUM(E64:E68) -> 4.4283333 | G69: TOTAL | I69: =I67*(1+H68) -> 54.2135
B71: RECHEIO | G71: BOMBOM SONHO DE VALSA | I71: =E74 -> 8.4
B72: leite condensado | C72: 1 | D72: ='1. Cadastro de Insumos'!E9 -> 6 | E72: =C72*D72 -> 6 | G72: Embalagem e Descartáveis | H72: 1 | I72: 2.5
B73: creme de leite | C73: 2 | D73: ='1. Cadastro de Insumos'!E10 -> 3 | E73: =C73*D73 -> 6
B74: BOMBOM SONHO DE VALSA | C74: 6 | D74: ='1. Cadastro de Insumos'!F17 -> 1.4 | E74: =C74*D74 -> 8.4 | G74: PREÇO FINAL DE VENDA SUGERIDO | I74: =SUM(I69:I73) -> 65.1135
E75: =SUM(E72:E74) -> 20.4
C76: CUSTO TOTAL DE INSUMOS: | E76: =SUM(E69,E75) -> 24.828333
B81: RECEITA: | C81: BOLO DE OURO BRANCO 1 KG | G81: PREÇO FINAL DE VENDA SUGERIDO
B83: Ingrediente | C83: Qtd na Receita | D83: Custo Unitário (R$) | E83: Subtotal Item (R$) | G83: Item de Custo | H83: Valor/Taxa | I83: Subtotal (R$)
B84: trigo | C84: 175 | D84: ='1. Cadastro de Insumos'!F2 -> 0.0028 | E84: =C84*D84 -> 0.49 | G84: Custo de Insumos (Automático) | I84: =SUM(E89:E93) -> 16.428333
B85: açúcar | C85: 150 | D85: ='1. Cadastro de Insumos'!F3 -> 0.004 | E85: =C85*D85 -> 0.6 | G85: Custos Fixos/Utilidades (Gás/Luz) - % | H85: 0.1 | I85: =I84*H85 -> 1.6428333
B86: ovo | C86: 3.5 | D86: ='1. Cadastro de Insumos'!F4 -> 0.66666667 | E86: =C86*D86 -> 2.3333333 | G86: Mão de Obra (Pro-labore) - % | H86: 0.2 | I86: =(I84+I85)*H86 -> 3.6142333
B87: fermento | C87: 7.5 | D87: ='1. Cadastro de Insumos'!F5 -> 0.044 | E87: =C87*D87 -> 0.33 | G87: SUBTOTAL (CUSTO DE PRODUÇÃO) | I87: =SUM(I84:I86) -> 21.6854
B88: emustab | C88: 15 | D88: ='1. Cadastro de Insumos'!F6 -> 0.045 | E88: =C88*D88 -> 0.675 | G88: Margem de Lucro Desejada - % | H88: 1.5
E89: =SUM(E84:E88) -> 4.4283333 | G89: TOTAL | I89: =I87*(1+H88) -> 54.2135
B91: RECHEIO | G91: BOMBOM SONHO DE VALSA | I91: =E94 -> 8.4
B92: leite condensado | C92: 1 | D92: ='1. Cadastro de Insumos'!E9 -> 6 | E92: =C92*D92 -> 6 | G92: Embalagem e Descartáveis | H92: 1 | I92: 2.5
B93: creme de leite | C93: 2 | D93: ='1. Cadastro de Insumos'!E10 -> 3 | E93: =C93*D93 -> 6
B94: BOMBOM SONHO DE VALSA | C94: 6 | D94: ='1. Cadastro de Insumos'!F16 -> 1.4 | E94: =C94*D94 -> 8.4 | G94: PREÇO FINAL DE VENDA SUGERIDO | I94: =SUM(I89:I93) -> 65.1135
E95: =SUM(E92:E94) -> 20.4
C96: CUSTO TOTAL DE INSUMOS: | E96: =SUM(E89,E95) -> 24.828333
B101: RECEITA: | C101: BOLO DE AMENDOIM 1 KG | G101: PREÇO FINAL DE VENDA SUGERIDO
B103: Ingrediente | C103: Qtd na Receita | D103: Custo Unitário (R$) | E103: Subtotal Item (R$) | G103: Item de Custo | H103: Valor/Taxa | I103: Subtotal (R$)
B104: trigo | C104: 175 | D104: ='1. Cadastro de Insumos'!F2 -> 0.0028 | E104: =C104*D104 -> 0.49 | G104: Custo de Insumos (Automático) | I104: =SUM(E109:E113) -> 16.428333
B105: açúcar | C105: 150 | D105: ='1. Cadastro de Insumos'!F3 -> 0.004 | E105: =C105*D105 -> 0.6 | G105: Custos Fixos/Utilidades (Gás/Luz) - % | H105: 0.1 | I105: =I104*H105 -> 1.6428333
B106: ovo | C106: 3.5 | D106: ='1. Cadastro de Insumos'!F4 -> 0.66666667 | E106: =C106*D106 -> 2.3333333 | G106: Mão de Obra (Pro-labore) - % | H106: 0.2 | I106: =(I104+I105)*H106 -> 3.6142333
B107: fermento | C107: 7.5 | D107: ='1. Cadastro de Insumos'!F5 -> 0.044 | E107: =C107*D107 -> 0.33 | G107: SUBTOTAL (CUSTO DE PRODUÇÃO) | I107: =SUM(I104:I106) -> 21.6854
B108: emustab | C108: 15 | D108: ='1. Cadastro de Insumos'!F6 -> 0.045 | E108: =C108*D108 -> 0.675 | G108: Margem de Lucro Desejada - % | H108: 1.5
E109: =SUM(E104:E108) -> 4.4283333 | G109: TOTAL | I109: =I107*(1+H108) -> 54.2135
B111: RECHEIO | G111: AMENDOIM | I111: =E114 -> 3
B112: leite condensado | C112: 1 | D112: ='1. Cadastro de Insumos'!E9 -> 6 | E112: =C112*D112 -> 6 | G112: Embalagem e Descartáveis | H112: 1 | I112: 2.5
B113: creme de leite | C113: 2 | D113: ='1. Cadastro de Insumos'!E10 -> 3 | E113: =C113*D113 -> 6
B114: AMENDOIM | C114: 100 | D114: ='1. Cadastro de Insumos'!F13 -> 0.03 | E114: =C114*D114 -> 3 | G114: PREÇO FINAL DE VENDA SUGERIDO | I114: =SUM(I109:I113) -> 59.7135
E115: =SUM(E112:E114) -> 15
C116: CUSTO TOTAL DE INSUMOS: | E116: =SUM(E109,E115) -> 19.428333
B121: RECEITA: | C121: BOLO DE MORANGO 1 KG | G121: PREÇO FINAL DE VENDA SUGERIDO
B123: Ingrediente | C123: Qtd na Receita | D123: Custo Unitário (R$) | E123: Subtotal Item (R$) | G123: Item de Custo | H123: Valor/Taxa | I123: Subtotal (R$)
B124: trigo | C124: 175 | D124: ='1. Cadastro de Insumos'!F2 -> 0.0028 | E124: =C124*D124 -> 0.49 | G124: Custo de Insumos (Automático) | I124: =SUM(E129:E133) -> 16.428333
B125: açúcar | C125: 150 | D125: ='1. Cadastro de Insumos'!F3 -> 0.004 | E125: =C125*D125 -> 0.6 | G125: Custos Fixos/Utilidades (Gás/Luz) - % | H125: 0.1 | I125: =I124*H125 -> 1.6428333
B126: ovo | C126: 3.5 | D126: ='1. Cadastro de Insumos'!F4 -> 0.66666667 | E126: =C126*D126 -> 2.3333333 | G126: Mão de Obra (Pro-labore) - % | H126: 0.2 | I126: =(I124+I125)*H126 -> 3.6142333
B127: fermento | C127: 7.5 | D127: ='1. Cadastro de Insumos'!F5 -> 0.044 | E127: =C127*D127 -> 0.33 | G127: SUBTOTAL (CUSTO DE PRODUÇÃO) | I127: =SUM(I124:I126) -> 21.6854
B128: emustab | C128: 15 | D128: ='1. Cadastro de Insumos'!F6 -> 0.045 | E128: =C128*D128 -> 0.675 | G128: Margem de Lucro Desejada - % | H128: 1.5
D129: ='1. Cadastro de Insumos'!F7 -> 0 | E129: =SUM(E124:E128) -> 4.4283333 | G129: TOTAL | I129: =I127*(1+H128) -> 54.2135
B131: RECHEIO | D131: ='1. Cadastro de Insumos'!F8 -> 0 | G131: MORANGO | I131: =E134 -> 15
B132: leite condensado | C132: 1 | D132: ='1. Cadastro de Insumos'!E9 -> 6 | E132: =C132*D132 -> 6 | G132: Embalagem e Descartáveis | H132: 1 | I132: 2.5
B133: creme de leite | C133: 2 | D133: ='1. Cadastro de Insumos'!E10 -> 3 | E133: =C133*D133 -> 6
B134: MORANGO | C134: 1 | D134: ='1. Cadastro de Insumos'!E15 -> 15 | E134: =C134*D134 -> 15 | G134: PREÇO FINAL DE VENDA SUGERIDO | I134: =SUM(I129:I133) -> 71.7135
E135: =SUM(E132:E134) -> 27
C136: CUSTO TOTAL DE INSUMOS: | E136: =SUM(E129,E135) -> 31.428333
